<?xml version="1.0" encoding="UTF-8"?>
<vconfkeylists>
  <filedef name="__VCONF_INTERNAL_IDLE_LOCK_KEYS_H__"/>
  <vconfkey type="string" name="db/idle_lock/bgset" layer="system" readPriv="http://tizen.org/privilege/internal/default/platform" writePriv="http://tizen.org/privilege/internal/default/platform">
    <header>VCONFKEY_IDLE_LOCK_BGSET</header>
    <val>/opt/share/settings/Wallpapers/Home_default.jpg</val>
    <creator/>
    <email/>
    <comment><![CDATA[ ]]></comment>
  </vconfkey>
  <vconfkey type="int32" name="memory/idle_lock/state" layer="memory" readPriv="http://tizen.org/privilege/internal/default/platform" writePriv="http://tizen.org/privilege/internal/default/platform">
    <header>VCONFKEY_IDLE_LOCK_STATE</header>
    <val>0</val>
    <creator/>
    <email/>
    <comment><![CDATA[ ]]></comment>
    <enumlist>
      <enumdata value="0">VCONFKEY_IDLE_UNLOCK</enumdata>
      <enumdata>VCONFKEY_IDLE_LOCK</enumdata>
      <enumdata>VCONFKEY_IDLE_LAUNCHING_LOCK</enumdata>
    </enumlist>
  </vconfkey>
  <vconfkey type="int32" name="memory/idle_lock/state_read_only" layer="memory" readPriv="http://tizen.org/privilege/internal/default/public" writePriv="http://tizen.org/privilege/internal/default/platform">
    <header>VCONFKEY_IDLE_LOCK_STATE_READ_ONLY</header>
    <val>0</val>
    <creator/>
    <email/>
    <comment><![CDATA[ ]]></comment>
  </vconfkey>
</vconfkeylists>
